<?xml version="1.0" encoding="Cp1252"?>

<product>
  <titledetail>
    <b202>01</b202>
    <titleelement>
      <b203>The Complete Guide to Securities Transactions</b203>
      <b209>Enhancing Investment Performance and Controlling Costs</b209>
    </titleelement>
  </titledetail>
</product>


<?xml version="1.0" encoding="Cp1252"?>

<product>
  <titledetail>
    <b202>01</b202>
    <titleelement>
      <b203>The Metaphorical Brain 2</b203>
      <b209>Neural Networks and Beyond</b209>
    </titleelement>
  </titledetail>
</product>


<?xml version="1.0" encoding="Cp1252"?>

<product>
  <titledetail>
    <b202>01</b202>
    <titleelement>
      <b203>Foundations of Soft Case-Based Reasoning</b203>
    </titleelement>
  </titledetail>
</product>


<?xml version="1.0" encoding="Cp1252"?>

<product>
  <titledetail>
    <b202>01</b202>
    <titleelement>
      <b203>Book 2 (Chapters 1-15)</b203>
    </titleelement>
  </titledetail>
</product>


<?xml version="1.0" encoding="Cp1252"?>

<product>
  <titledetail>
    <b202>01</b202>
    <titleelement>
      <b203>Mastering Documentation</b203>
      <b209>With Document Masters for Systems Development, Control, and Delivery</b209>
    </titleelement>
  </titledetail>
</product>


<?xml version="1.0" encoding="Cp1252"?>

<product>
  <titledetail>
    <b202>01</b202>
    <titleelement>
      <b203>Book 2 (Chapters 1-15)</b203>
    </titleelement>
  </titledetail>
</product>


<?xml version="1.0" encoding="Cp1252"?>

<product>
  <titledetail>
    <b202>01</b202>
    <titleelement />
  </titledetail>
</product>


<?xml version="1.0" encoding="Cp1252"?>

<product>
  <titledetail>
    <b202>01</b202>
    <titleelement>
      <b203>Rendezvous with ADA</b203>
      <b209>Programmers Introduction</b209>
    </titleelement>
  </titledetail>
</product>

